visarate/__init__.py
visarate/rate.py
visarate-0.4.0.dist-info/LICENSE
visarate-0.4.0.dist-info/METADATA
visarate-0.4.0.dist-info/WHEEL
visarate-0.4.0.dist-info/RECORD
