Metadata-Version: 2.1
Name: visarate
Version: 0.4.0
Summary: 
Author: narumi
Author-email: toucans-cutouts0f@icloud.com
Requires-Python: >=3.9,<4.0
Classifier: Programming Language :: Python :: 3
Classifier: Programming Language :: Python :: 3.9
Classifier: Programming Language :: Python :: 3.10
Classifier: Programming Language :: Python :: 3.11
Classifier: Programming Language :: Python :: 3.12
Requires-Dist: httpx (>=0.27.0,<0.28.0)
Requires-Dist: pydantic (>=2.6.1,<3.0.0)
Requires-Dist: tenacity (>=8.2.3,<9.0.0)
